multiplier.v
`timescale 1ns/1ns
module multiplier (out,a_in,b_in,clock,start,reset,finish,bcd);
   parameter N = 8;

   output [(((N*2)/3)+1)*4 - 1:0]bcd;
   output [(N*2)-1:0]out;
   output finish;

   input start;
   input clock;
   input reset;
   input [N-1 : 0]a_in; 
   input [N-1 : 0]b_in;

   reg[(((N*2)/3)+1)*4 - 1:0]bcd_reg = 0;
   reg[(N*2)-1:0]out_reg;
   reg finish_reg = 0;
   reg [(N*2)-1:0]a_in_reg; 
   reg [(N*2)-1:0]b_in_reg;
   reg [8:0]bits; 

   assign bcd = bcd_reg;
   assign out = out_reg;
   assign finish = finish_reg;
   integer i;

   always @(negedge reset) 
   begin
     out_reg = 0;
     a_in_reg = 0;
     b_in_reg = 0; 
   end

   always @(posedge clock) 
   begin
    if (!reset) 
    begin
      case (start)
       1'b0 : begin
                a_in_reg = a_in;
                b_in_reg = b_in;
                bits = N;
                finish_reg = 0;
                out_reg = 0;
                bcd_reg = 0;
                $display("Values loaded into the input register");
              end
       1'b1 :begin
               if (b_in_reg[0] == 1) 
               begin
                 out_reg = out_reg + a_in_reg; 
               end
               bits = bits - 1;
               a_in_reg = a_in_reg<<1;
               b_in_reg = b_in_reg>>1;
             end        
      endcase 
      if (bits == 0) 
      begin
        $display("Multiplication completed!!");
        finish_reg = 1'b1;
        for (i = 0;i < (N*2);i = i+1) 
        begin
          if(3 <= (((N*2)/3)+1)*4 - 1 && bcd_reg[3:0] >= 5)
             bcd_reg[3:0] = bcd_reg[3:0] + 3;
          if(7 <= (((N*2)/3)+1)*4 - 1 && bcd_reg[7:4] >= 5)
             bcd_reg[7:4] = bcd_reg[7:4] + 3;
          if(11 <= (((N*2)/3)+1)*4 - 1 && bcd_reg[11:8] >= 5)
             bcd_reg[11:8] = bcd_reg[11:8] + 3;
          if(15 <= (((N*2)/3)+1)*4 - 1 && bcd_reg[15:12] >= 5)
             bcd_reg[15:12] = bcd_reg[15:12] + 3;    
          bcd_reg = {bcd_reg[(((N*2)/3)+1)*4 - 2:0],out_reg[(N*2) -1 -i]};            
        end  
        $display("Conversion of binary to BCD completed");
      end   
    end 
   end
endmodule

multiplier_tb.v
`timescale 1ns/1ns
`include "multiplier.v"
module multiplier_tb;
    parameter n_bits = 5;
    reg [n_bits-1:0]a_in;
    reg [n_bits-1:0]b_in;
    reg clock;
    reg start;
    reg reset;
    wire [(n_bits*2)-1:0]out;
    wire finish;
    wire [(((n_bits*2)/3)+1)*4-1:0]bcd;

    multiplier uut(
        .out(out),
        .a_in(a_in),
        .b_in(b_in),
        .clock(clock),
        .start(start),
        .reset(reset),
        .finish(finish),
        .bcd(bcd));
    defparam uut.N = n_bits;
    initial 
    begin
      $dumpfile("multiplier.vcd");
      $dumpvars(0,multiplier_tb);  
      forever #50 clock = ~clock;    
    end

    initial 
    begin
      a_in = 0;
      b_in = 0;
      clock = 0;
      start = 0;
      reset = 0;
      #100;
      a_in = 'd26;
      b_in = 'd30;
      start = 0;
      #200 start = 1;
      #1000; 
      a_in = 'd13; b_in = 'd13;
      start = 0;
      #200 start = 1; 
      #1000;   
    end

    initial begin
        #2500 $finish;
    end    
endmodule

multiplier.vcd
$date
	Wed Jul 17 13:41:11 2024
$end
$version
	Icarus Verilog
$end
$timescale
	1ns
$end
$scope module multiplier_tb $end
$var wire 10 ! out [9:0] $end
$var wire 1 " finish $end
$var wire 16 # bcd [15:0] $end
$var reg 5 $ a_in [4:0] $end
$var reg 5 % b_in [4:0] $end
$var reg 1 & clock $end
$var reg 1 ' reset $end
$var reg 1 ( start $end
$scope module uut $end
$var wire 5 ) a_in [4:0] $end
$var wire 5 * b_in [4:0] $end
$var wire 16 + bcd [15:0] $end
$var wire 1 & clock $end
$var wire 1 " finish $end
$var wire 10 , out [9:0] $end
$var wire 1 ' reset $end
$var wire 1 ( start $end
$var reg 10 - a_in_reg [9:0] $end
$var reg 10 . b_in_reg [9:0] $end
$var reg 16 / bcd_reg [15:0] $end
$var reg 9 0 bits [8:0] $end
$var reg 1 1 finish_reg $end
$var reg 10 2 out_reg [9:0] $end
$var integer 32 3 i [31:0] $end
$upscope $end
$upscope $end
$enddefinitions $end
#0
$dumpvars
bx 3
b0 2
01
bx 0
b0 /
b0 .
b0 -
b0 ,
b0 +
b0 *
b0 )
0(
0'
0&
b0 %
b0 $
b0 #
0"
b0 !
$end
#50
b101 0
1&
#100
0&
b11110 %
b11110 *
b11010 $
b11010 )
#150
b11110 .
b11010 -
1&
#200
0&
#250
1&
#300
0&
1(
#350
b1111 .
b110100 -
b100 0
1&
#400
0&
#450
b111 .
b1101000 -
b11 0
b110100 !
b110100 ,
b110100 2
1&
#500
0&
#550
b11 .
b11010000 -
b10 0
b10011100 !
b10011100 ,
b10011100 2
1&
#600
0&
#650
b1 .
b110100000 -
b1 0
b101101100 !
b101101100 ,
b101101100 2
1&
#700
0&
#750
b11110000000 #
b11110000000 +
b11110000000 /
b1010 3
1"
11
b0 .
b1101000000 -
b0 0
b1100001100 !
b1100001100 ,
b1100001100 2
1&
#800
0&
#850
b1010000000 -
b111111111 0
1&
#900
0&
#950
b100000000 -
b111111110 0
1&
#1000
0&
#1050
b1000000000 -
b111111101 0
1&
#1100
0&
#1150
b0 -
b111111100 0
1&
#1200
0&
#1250
b111111011 0
1&
#1300
0&
0(
b1101 %
b1101 *
b1101 $
b1101 )
#1350
b0 #
b0 +
b0 /
b0 !
b0 ,
b0 2
0"
01
b101 0
b1101 .
b1101 -
1&
#1400
0&
#1450
1&
#1500
0&
1(
#1550
b110 .
b11010 -
b100 0
b1101 !
b1101 ,
b1101 2
1&
#1600
0&
#1650
b11 .
b110100 -
b11 0
1&
#1700
0&
#1750
b1 .
b1101000 -
b10 0
b1000001 !
b1000001 ,
b1000001 2
1&
#1800
0&
#1850
b0 .
b11010000 -
b1 0
b10101001 !
b10101001 ,
b10101001 2
1&
#1900
0&
#1950
b101101001 #
b101101001 +
b101101001 /
b1010 3
1"
11
b110100000 -
b0 0
1&
#2000
0&
#2050
b1101000000 -
b111111111 0
1&
#2100
0&
#2150
b1010000000 -
b111111110 0
1&
#2200
0&
#2250
b100000000 -
b111111101 0
1&
#2300
0&
#2350
b1000000000 -
b111111100 0
1&
#2400
0&
#2450
b0 -
b111111011 0
1&
